LICENSE
README.md
setup.py
fruitmod/__init__.py
fruitmod.egg-info/PKG-INFO
fruitmod.egg-info/SOURCES.txt
fruitmod.egg-info/dependency_links.txt
fruitmod.egg-info/top_level.txt