Metadata-Version: 2.4
Name: fruitmod
Version: 0.5.5
Summary: A module for seven grade of high school
Author: M.P.Abdi
Author-email: m.p.abdi90@gmail.com
License: MIT
Classifier: Programming Language :: Python :: 3
Classifier: Operating System :: OS Independent
Requires-Python: >= 3.6
License-File: LICENSE
Dynamic: author
Dynamic: author-email
Dynamic: classifier
Dynamic: description
Dynamic: description-content-type
Dynamic: license
Dynamic: license-file
Dynamic: requires-python
Dynamic: summary
